clean_plot/__init__.py
clean_plot/_modidx.py
clean_plot/_nbdev.py
clean_plot/core.py
clean_plot/errors.py
clean_plot/functions.py
clean_plot/heatmaps_novels.py
clean_plot/lexical.py
clean_plot/pickle.py
clean_plot/trial.py
clean_plot/utils.py
clean_plot/plot/__init__.py
clean_plot/plot/utils.py
clean_plot-0.0.13.dist-info/LICENSE
clean_plot-0.0.13.dist-info/METADATA
clean_plot-0.0.13.dist-info/WHEEL
clean_plot-0.0.13.dist-info/entry_points.txt
clean_plot-0.0.13.dist-info/top_level.txt
clean_plot-0.0.13.dist-info/RECORD
