Metadata-Version: 2.1
Name: clean-plot
Version: 0.0.13
Summary: clean_plot simplifies cleaning text files for creation of embeddings and making plots from it
Home-page: https://github.com/deven367/clean_plot/tree/master/
Author: Deven Mistry
Author-email: masterdeven@gmail.com
License: Apache Software License 2.0
Keywords: cleaning tokenizing embeddings plotting
Classifier: Development Status :: 3 - Alpha
Classifier: Intended Audience :: Developers
Classifier: Natural Language :: English
Classifier: Programming Language :: Python :: 3.6
Classifier: Programming Language :: Python :: 3.7
Classifier: Programming Language :: Python :: 3.8
Classifier: Programming Language :: Python :: 3.9
Classifier: Programming Language :: Python :: 3.10
Classifier: License :: OSI Approved :: Apache Software License
Requires-Python: >=3.6
License-File: LICENSE
Requires-Dist: numpy
Requires-Dist: pandas
Requires-Dist: seaborn
Requires-Dist: sklearn
Requires-Dist: nltk
Requires-Dist: unidecode
Requires-Dist: fastcore
Provides-Extra: dev
